setup.py
client/__init__.py
client/add_contact.py
client/database.py
client/del_contact.py
client/main_window.py
client/main_window_conv.py
client/start_dialog.py
client/transport.py
common/__init__.py
common/decos.py
common/descryptors.py
common/errors.py
common/metaclasses.py
common/utils.py
common/variables.py
logs/__init__.py
logs/config_client_log.py
logs/config_server_log.py
messenger_client_project_december.egg-info/PKG-INFO
messenger_client_project_december.egg-info/SOURCES.txt
messenger_client_project_december.egg-info/dependency_links.txt
messenger_client_project_december.egg-info/requires.txt
messenger_client_project_december.egg-info/top_level.txt
unit_tests/__init__.py
unit_tests/test_client.py
unit_tests/test_utils.py